pymodaq_plugins_srs/__init__.py
pymodaq_plugins_srs/utils.py
pymodaq_plugins_srs/daq_move_plugins/__init__.py
pymodaq_plugins_srs/daq_viewer_plugins/__init__.py
pymodaq_plugins_srs/daq_viewer_plugins/plugins_0D/__init__.py
pymodaq_plugins_srs/daq_viewer_plugins/plugins_0D/daq_0Dviewer_LockInSR830.py
pymodaq_plugins_srs/daq_viewer_plugins/plugins_0D/daq_0Dviewer_SR830.py
pymodaq_plugins_srs/daq_viewer_plugins/plugins_1D/__init__.py
pymodaq_plugins_srs/daq_viewer_plugins/plugins_2D/__init__.py
pymodaq_plugins_srs/daq_viewer_plugins/plugins_ND/__init__.py
pymodaq_plugins_srs/exporters/__init__.py
pymodaq_plugins_srs/extensions/__init__.py
pymodaq_plugins_srs/hardware/__init__.py
pymodaq_plugins_srs/models/PIDModelTemplate.py
pymodaq_plugins_srs/models/__init__.py
pymodaq_plugins_srs/resources/VERSION
pymodaq_plugins_srs/resources/__init__.py
pymodaq_plugins_srs/resources/config_template.toml
pymodaq_plugins_srs/scanners/__init__.py
pymodaq_plugins_srs-0.0.2.dist-info/LICENSE
pymodaq_plugins_srs-0.0.2.dist-info/METADATA
pymodaq_plugins_srs-0.0.2.dist-info/WHEEL
pymodaq_plugins_srs-0.0.2.dist-info/entry_points.txt
pymodaq_plugins_srs-0.0.2.dist-info/top_level.txt
pymodaq_plugins_srs-0.0.2.dist-info/RECORD
